aiotk/__init__.py
aiotk/_cancel.py
aiotk/_ctrlc.py
aiotk/_io.py
aiotk/_mempipe.py
aiotk/_monkey.py
aiotk/_pool.py
aiotk/_posix.py
aiotk/_sched.py
aiotk/_stack.py
aiotk/_tcp.py
aiotk/_testing.py
aiotk/_typing.py
aiotk/_udp.py
aiotk-0.5.0.dist-info/DESCRIPTION.rst
aiotk-0.5.0.dist-info/METADATA
aiotk-0.5.0.dist-info/RECORD
aiotk-0.5.0.dist-info/WHEEL
aiotk-0.5.0.dist-info/metadata.json
aiotk-0.5.0.dist-info/top_level.txt
