Metadata-Version: 2.0
Name: aiotk
Version: 0.5.0
Summary: aiotk: asyncio toolkit
Home-page: https://github.com/AndreLouisCaron/aiotk
Author: Andre Caron
Author-email: andre.l.caron@gmail.com
License: UNKNOWN
Platform: UNKNOWN
Requires-Dist: typing-extensions (>=3.6.5)
